ofdparser/__init__.py
ofdparser/ofdparser.py
test/__init__.py
test/test.py
ofdparser-0.0.8.dist-info/LICENSE
ofdparser-0.0.8.dist-info/METADATA
ofdparser-0.0.8.dist-info/WHEEL
ofdparser-0.0.8.dist-info/top_level.txt
ofdparser-0.0.8.dist-info/RECORD
