Metadata-Version: 2.1
Name: ofdparser
Version: 0.0.8
Summary: ofdparser
Home-page: https://github.com/renoyuan/pyofdpaerser
Author: renoyuan
Author-email: renoyuan@foxmail.com
License: UNKNOWN
Platform: UNKNOWN
Classifier: Programming Language :: Python :: 3
Classifier: License :: OSI Approved :: MIT License
Classifier: Operating System :: OS Independent
Requires-Python: >=3.6
License-File: LICENSE
